{
    "success": true,
    "results": 104,
    "total": 1104,
    "parameters": {
        "player": "76561198005943577",
        "uploader": null,
        "title": null,
        "map": null,
        "limit": 1000,
        "offset": 1000
    },
    "logs": [
        {
            "id": 1104088,
            "title": "The Meme Fortress: RED vs BLU",
            "map": "cp_gullywash_final1",
            "date": 1447070552,
            "views": 222,
            "players": 12
        },
        {
            "id": 1104060,
            "title": "ozfortress.com 5: RED vs BLU",
            "map": "koth_viaduct_pro5",
            "date": 1447063144,
            "views": 179,
            "players": 12
        },
        {
            "id": 1104044,
            "title": "ozfortress.com 5: RED vs BLU",
            "map": "cp_badlands",
            "date": 1447062025,
            "views": 149,
            "players": 13
        },
        {
            "id": 1096367,
            "title": "SMTF2: 420 vs BLU",
            "map": "cp_gullywash_final1",
            "date": 1446637823,
            "views": 97,
            "players": 12
        },
        {
            "id": 1096361,
            "title": "SMTF2: RED vs BLU",
            "map": "cp_snakewater_final1",
            "date": 1446636908,
            "views": 187,
            "players": 12
        },
        {
            "id": 1096350,
            "title": "ozfortress.com 7: BAWSAQ vs XD",
            "map": "cp_badlands",
            "date": 1446634901,
            "views": 129,
            "players": 12
        },
        {
            "id": 1096338,
            "title": "ozfortress.com 7: RED vs BLU",
            "map": "cp_granary_pro_b10",
            "date": 1446633614,
            "views": 109,
            "players": 12
        },
        {
            "id": 1092178,
            "title": "ozfortress.com 4: RED vs :):>",
            "map": "cp_gullywash_final1",
            "date": 1446370411,
            "views": 185,
            "players": 13
        },
        {
            "id": 1088128,
            "title": "SMTF2: RED vs BLU",
            "map": "cp_gullywash_final1",
            "date": 1446121728,
            "views": 210,
            "players": 12
        },
        {
            "id": 1088123,
            "title": "SMTF2: RED vs BLU",
            "map": "cp_snakewater_final1",
            "date": 1446119363,
            "views": 121,
            "players": 13
        },
        {
            "id": 1088116,
            "title": "ozfortress.com 4: RED vs BLU",
            "map": "cp_badlands",
            "date": 1446117079,
            "views": 141,
            "players": 12
        },
        {
            "id": 1088097,
            "title": "ozfortress.com 4: RED vs Clown9",
            "map": "cp_process_final",
            "date": 1446115789,
            "views": 173,
            "players": 13
        },
        {
            "id": 1083820,
            "title": "SMTF2: RED vs memez",
            "map": "cp_gullywash_final1",
            "date": 1445860395,
            "views": 155,
            "players": 12
        },
        {
            "id": 996321,
            "title": "ozfortress.com 7: RED vs BLU",
            "map": "cp_granary_pro_b10",
            "date": 1440680118,
            "views": 291,
            "players": 12
        },
        {
            "id": 996317,
            "title": "ozfortress.com 7: RED vs BLU",
            "map": "cp_badlands",
            "date": 1440677869,
            "views": 240,
            "players": 12
        },
        {
            "id": 996288,
            "title": "ozfortress.com 7: RED vs BLU",
            "map": "cp_badlands",
            "date": 1440677630,
            "views": 298,
            "players": 12
        },
        {
            "id": 996251,
            "title": "ozfortress.com 7: RED vs BLU",
            "map": "cp_sunshine_rc8",
            "date": 1440675608,
            "views": 260,
            "players": 12
        },
        {
            "id": 996227,
            "title": "ozfortress.com 7: RED vs BLU",
            "map": "cp_snakewater_final1",
            "date": 1440672573,
            "views": 85,
            "players": 12
        },
        {
            "id": 996204,
            "title": "ozfortress.com 7: RED vs BLU",
            "map": "cp_badlands",
            "date": 1440671733,
            "views": 94,
            "players": 13
        },
        {
            "id": 992012,
            "title": "ozfortress.com 4: RED vs BLU",
            "map": "koth_product_rc8",
            "date": 1440414108,
            "views": 108,
            "players": 12
        },
        {
            "id": 991988,
            "title": "ozfortress.com 4: RED vs BLU",
            "map": "cp_sunshine_rc8",
            "date": 1440413164,
            "views": 140,
            "players": 13
        },
        {
            "id": 990365,
            "title": "ozfortress.com 6: RED vs BLU",
            "map": "cp_granary_pro_b10",
            "date": 1440327609,
            "views": 96,
            "players": 12
        },
        {
            "id": 990332,
            "title": "ozfortress.com 6: RED vs butt",
            "map": "cp_badlands",
            "date": 1440326437,
            "views": 120,
            "players": 12
        },
        {
            "id": 985668,
            "title": "ozfortress.com 9: RED vs BLU",
            "map": "koth_product_rc8",
            "date": 1440072627,
            "views": 85,
            "players": 12
        },
        {
            "id": 985644,
            "title": "ozfortress.com 9: RED vs BLU",
            "map": "cp_process_final",
            "date": 1440070518,
            "views": 182,
            "players": 12
        },
        {
            "id": 985617,
            "title": "ozfortress.com 2: RED vs BLU",
            "map": "cp_process_final",
            "date": 1440068740,
            "views": 76,
            "players": 12
        },
        {
            "id": 985600,
            "title": "ozfortress.com 2: RED vs BLU",
            "map": "cp_snakewater_final1",
            "date": 1440066885,
            "views": 73,
            "players": 12
        },
        {
            "id": 980983,
            "title": "ozfortress.com 7: RED vs BLU",
            "map": "cp_snakewater_final1",
            "date": 1439813889,
            "views": 88,
            "players": 12
        },
        {
            "id": 980957,
            "title": "ozfortress.com 7: RED vs BLU",
            "map": "cp_process_final",
            "date": 1439811952,
            "views": 124,
            "players": 13
        },
        {
            "id": 980933,
            "title": "ozfortress.com 7: RED vs BLU",
            "map": "cp_snakewater_final1",
            "date": 1439809451,
            "views": 67,
            "players": 12
        },
        {
            "id": 980895,
            "title": "ozfortress.com 7: wRED vs BLU",
            "map": "cp_process_final",
            "date": 1439808479,
            "views": 125,
            "players": 12
        },
        {
            "id": 979205,
            "title": "ozfortress.com 3: RED vs BLU",
            "map": "cp_gullywash_final1",
            "date": 1439726767,
            "views": 99,
            "players": 13
        },
        {
            "id": 979175,
            "title": "ozfortress.com 3: RED vs BLU",
            "map": "cp_snakewater_final1",
            "date": 1439725360,
            "views": 108,
            "players": 12
        },
        {
            "id": 979152,
            "title": "ozfortress.com 3: RED vs BLU",
            "map": "koth_product_rc8",
            "date": 1439723161,
            "views": 118,
            "players": 12
        },
        {
            "id": 979119,
            "title": "ozfortress.com 3: RED vs BLU",
            "map": "cp_process_final",
            "date": 1439721912,
            "views": 117,
            "players": 12
        },
        {
            "id": 970772,
            "title": "ozfortress.com 5: goon vs BLU",
            "map": "cp_badlands",
            "date": 1439293184,
            "views": 117,
            "players": 12
        },
        {
            "id": 970694,
            "title": "ozfortress.com 5: RED vs BLU",
            "map": "cp_process_final",
            "date": 1439289206,
            "views": 134,
            "players": 13
        },
        {
            "id": 967297,
            "title": "ozfortress.com 10: RED vs BLU",
            "map": "cp_granary_pro_b10",
            "date": 1439122051,
            "views": 216,
            "players": 13
        },
        {
            "id": 967274,
            "title": "ozfortress.com 10: RED vs BLU",
            "map": "cp_badlands",
            "date": 1439119778,
            "views": 249,
            "players": 12
        },
        {
            "id": 967261,
            "title": "ozfortress.com 10: RED vs BLU",
            "map": "cp_badlands",
            "date": 1439117908,
            "views": 105,
            "players": 12
        },
        {
            "id": 967229,
            "title": "ozfortress.com 10: RED vs BLU",
            "map": "cp_granary_pro_b10",
            "date": 1439116877,
            "views": 93,
            "players": 12
        },
        {
            "id": 962244,
            "title": "ozfortress.com 6: RED vs BLU",
            "map": "cp_granary_pro_b10",
            "date": 1438863383,
            "views": 180,
            "players": 12
        },
        {
            "id": 962220,
            "title": "ozfortress.com 6: RED vs BLU",
            "map": "cp_gullywash_final1",
            "date": 1438861082,
            "views": 217,
            "players": 12
        },
        {
            "id": 962189,
            "title": "ozfortress.com 6: RED vs BLU",
            "map": "cp_gullywash_final1",
            "date": 1438858671,
            "views": 76,
            "players": 12
        },
        {
            "id": 962157,
            "title": "ozfortress.com 6: RED vs BLU",
            "map": "cp_granary_pro_b10",
            "date": 1438857689,
            "views": 68,
            "players": 14
        },
        {
            "id": 959446,
            "title": "ozfortress.com 14: RED vs BLU",
            "map": "koth_product_rc8",
            "date": 1438690674,
            "views": 86,
            "players": 12
        },
        {
            "id": 959401,
            "title": "ozfortress.com 14: RED vs BLU",
            "map": "cp_gullywash_final1",
            "date": 1438688379,
            "views": 73,
            "players": 12
        },
        {
            "id": 959385,
            "title": "ozfortress.com 14: RED vs BLU",
            "map": "cp_gullywash_final1",
            "date": 1438685969,
            "views": 68,
            "players": 12
        },
        {
            "id": 959349,
            "title": "ozfortress.com 14: RED vs BLU",
            "map": "cp_granary_pro_b10",
            "date": 1438685163,
            "views": 104,
            "players": 13
        },
        {
            "id": 957738,
            "title": "ozfortress.com 8: RED vs BLU",
            "map": "cp_badlands",
            "date": 1438601187,
            "views": 129,
            "players": 12
        },
        {
            "id": 957708,
            "title": "ozfortress.com 8: RED vs 3BLU",
            "map": "cp_gullywash_final1",
            "date": 1438599818,
            "views": 108,
            "players": 14
        },
        {
            "id": 957691,
            "title": "ozfortress.com 8: RED vs BLU",
            "map": "cp_granary_pro_b10",
            "date": 1438598200,
            "views": 229,
            "players": 13
        },
        {
            "id": 957684,
            "title": "ozfortress.com 8: RED vs BLU",
            "map": "cp_granary_pro_b10",
            "date": 1438597141,
            "views": 217,
            "players": 11
        },
        {
            "id": 947730,
            "title": "ozfortress.com 5: RED vs BLU",
            "map": "koth_product_rc8",
            "date": 1438084374,
            "views": 112,
            "players": 12
        },
        {
            "id": 947695,
            "title": "ozfortress.com 12: RED vs BLU",
            "map": "cp_snakewater_final1",
            "date": 1438081527,
            "views": 99,
            "players": 12
        },
        {
            "id": 947674,
            "title": "ozfortress.com 12: RED vs BLU",
            "map": "koth_product_rc8",
            "date": 1438079717,
            "views": 124,
            "players": 12
        },
        {
            "id": 944414,
            "title": "ozfortress.com 13: RED vs BLU",
            "map": "koth_viaduct_pro5",
            "date": 1437912007,
            "views": 76,
            "players": 12
        },
        {
            "id": 944360,
            "title": "ozfortress.com 13: RED vs poppnk",
            "map": "cp_sunshine_rc8",
            "date": 1437910563,
            "views": 136,
            "players": 12
        },
        {
            "id": 944338,
            "title": "ozfortress.com 10: RED vs BLU",
            "map": "koth_viaduct_pro5",
            "date": 1437908421,
            "views": 114,
            "players": 12
        },
        {
            "id": 944306,
            "title": "ozfortress.com 10: RED vs BLU",
            "map": "cp_snakewater_final1",
            "date": 1437907157,
            "views": 146,
            "players": 12
        },
        {
            "id": 933898,
            "title": "ozfortress.com 2: RED vs BLU",
            "map": "cp_process_final",
            "date": 1437394398,
            "views": 106,
            "players": 12
        },
        {
            "id": 933872,
            "title": "ozfortress.com 2: RED vs BLU",
            "map": "cp_sunshine_rc8",
            "date": 1437392326,
            "views": 105,
            "players": 12
        },
        {
            "id": 933848,
            "title": "ozfortress.com 2: RED vs BLU",
            "map": "cp_sunshine_rc8",
            "date": 1437389965,
            "views": 86,
            "players": 12
        },
        {
            "id": 933818,
            "title": "ozfortress.com 2: RED vs BLU",
            "map": "cp_process_final",
            "date": 1437388935,
            "views": 99,
            "players": 12
        },
        {
            "id": 932065,
            "title": "ozfortress.com 16: RED vs BLU",
            "map": "cp_snakewater_final1",
            "date": 1437308181,
            "views": 127,
            "players": 13
        },
        {
            "id": 932028,
            "title": "ozfortress.com 16: RED vs BLU",
            "map": "cp_process_final",
            "date": 1437306210,
            "views": 95,
            "players": 12
        },
        {
            "id": 931999,
            "title": "ozfortress.com 13: RED vs BLU",
            "map": "cp_badlands",
            "date": 1437304165,
            "views": 175,
            "players": 13
        },
        {
            "id": 931966,
            "title": "ozfortress.com 13: RED vs BLU",
            "map": "cp_process_final",
            "date": 1437302205,
            "views": 189,
            "players": 12
        },
        {
            "id": 926645,
            "title": "ozfortress.com 5: RED vs BLU",
            "map": "cp_process_final",
            "date": 1437046309,
            "views": 85,
            "players": 12
        },
        {
            "id": 926606,
            "title": "ozfortress.com 5: ripe vs BLU",
            "map": "cp_badlands",
            "date": 1437044084,
            "views": 148,
            "players": 12
        },
        {
            "id": 926578,
            "title": "ozfortress.com 5: RED vs BLU",
            "map": "cp_badlands",
            "date": 1437040830,
            "views": 120,
            "players": 13
        },
        {
            "id": 926549,
            "title": "ozfortress.com 5: RED vs BLU",
            "map": "cp_process_final",
            "date": 1437039730,
            "views": 95,
            "players": 12
        },
        {
            "id": 921376,
            "title": "ozfortress.com 7: RED vs BLU",
            "map": "cp_process_final",
            "date": 1436788016,
            "views": 88,
            "players": 12
        },
        {
            "id": 921343,
            "title": "ozfortress.com 7: RED vs BLU",
            "map": "cp_badlands",
            "date": 1436787321,
            "views": 92,
            "players": 12
        },
        {
            "id": 921313,
            "title": "ozfortress.com 7: mkdsm vs BLU",
            "map": "cp_granary_pro_b9",
            "date": 1436785045,
            "views": 74,
            "players": 13
        },
        {
            "id": 921279,
            "title": "ozfortress.com 7: RED vs BLU",
            "map": "cp_process_final",
            "date": 1436783830,
            "views": 109,
            "players": 12
        },
        {
            "id": 919997,
            "title": "ozfortress.com 14: fkuboy vs dhboys",
            "map": "cp_badlands",
            "date": 1436703110,
            "views": 138,
            "players": 13
        },
        {
            "id": 919979,
            "title": "ozfortress.com 14: RED vs BLU",
            "map": "cp_process_final",
            "date": 1436701070,
            "views": 101,
            "players": 12
        },
        {
            "id": 916557,
            "title": "ozfortress.com 7: RED vs BLU",
            "map": "koth_ashville_rc1",
            "date": 1436525457,
            "views": 105,
            "players": 8
        },
        {
            "id": 916535,
            "title": "ozfortress.com 7: RED vs BLU",
            "map": "koth_ashville_rc1",
            "date": 1436525065,
            "views": 121,
            "players": 8
        },
        {
            "id": 913375,
            "title": "ozfortress.com 6: RED vs BLU",
            "map": "cp_snakewater_final1",
            "date": 1436358304,
            "views": 92,
            "players": 12
        },
        {
            "id": 913341,
            "title": "ozfortress.com 6: RED vs BLU",
            "map": "cp_granary_pro_b9",
            "date": 1436356160,
            "views": 99,
            "players": 12
        },
        {
            "id": 913315,
            "title": "ozfortress.com 6: RED vs BLU",
            "map": "cp_badlands",
            "date": 1436353674,
            "views": 85,
            "players": 13
        },
        {
            "id": 909974,
            "title": "ozfortress.com 5: RED vs BLU",
            "map": "cp_badlands",
            "date": 1436184707,
            "views": 84,
            "players": 13
        },
        {
            "id": 909928,
            "title": "ozfortress.com 5: REDc vs BLU",
            "map": "cp_process_final",
            "date": 1436182714,
            "views": 91,
            "players": 12
        },
        {
            "id": 909892,
            "title": "ozfortress.com 5: goon vs gogog",
            "map": "cp_badlands",
            "date": 1436180275,
            "views": 183,
            "players": 13
        },
        {
            "id": 909858,
            "title": "ozfortress.com 5: bgkev vs BLU",
            "map": "koth_viaduct_pro5",
            "date": 1436178800,
            "views": 151,
            "players": 12
        },
        {
            "id": 907053,
            "title": "ozfortress.com 1: RED vs BLU",
            "map": "koth_ultiduo_r_b7",
            "date": 1436022209,
            "views": 59,
            "players": 4
        },
        {
            "id": 907029,
            "title": "ozfortress.com 1: joad vs BLU",
            "map": "koth_ultiduo_r_b7",
            "date": 1436020620,
            "views": 57,
            "players": 4
        },
        {
            "id": 906980,
            "title": "ozfortress.com 1: joad vs BLU",
            "map": "koth_ultiduo_r_b7",
            "date": 1436019971,
            "views": 55,
            "players": 4
        },
        {
            "id": 906193,
            "title": "TF2Center Lobby #458023",
            "map": "cp_process_final",
            "date": 1435974005,
            "views": 69,
            "players": 12
        },
        {
            "id": 906131,
            "title": "nKH!: wRED vs BLU",
            "map": "cp_process_final",
            "date": 1435973916,
            "views": 72,
            "players": 12
        },
        {
            "id": 902076,
            "title": "ozfortress.com 10: RED vs fuck",
            "map": "cp_badlands",
            "date": 1435752492,
            "views": 140,
            "players": 12
        },
        {
            "id": 902039,
            "title": "ozfortress.com 10: RED vs BLU",
            "map": "cp_badlands",
            "date": 1435749679,
            "views": 98,
            "players": 12
        },
        {
            "id": 902013,
            "title": "ozfortress.com 10: RED vs BLU",
            "map": "cp_granary_pro_b9",
            "date": 1435748673,
            "views": 83,
            "players": 12
        },
        {
            "id": 901989,
            "title": "ozfortress.com 10: rup vs BLU",
            "map": "cp_process_final",
            "date": 1435747251,
            "views": 97,
            "players": 13
        },
        {
            "id": 834365,
            "title": "TF2Center Lobby #420734",
            "map": "koth_lakeside_final",
            "date": 1432449483,
            "views": 150,
            "players": 19
        },
        {
            "id": 705544,
            "title": "TF2Center Lobby #351489",
            "map": "koth_lakeside_final",
            "date": 1425647336,
            "views": 118,
            "players": 18
        },
        {
            "id": 705427,
            "title": "TF2Center Lobby #351383",
            "map": "koth_ashville_rc1",
            "date": 1425628657,
            "views": 154,
            "players": 21
        },
        {
            "id": 684136,
            "title": "serveme.tf - BLU vs sak",
            "map": "cp_badlands",
            "date": 1424487126,
            "views": 82,
            "players": 12
        },
        {
            "id": 684135,
            "title": "TF2Center Lobby #339894",
            "map": "cp_badlands",
            "date": 1424487123,
            "views": 115,
            "players": 12
        },
        {
            "id": 352647,
            "title": "TF2Center Lobby #149852",
            "map": "ctf_2fort",
            "date": 1404650293,
            "views": 217,
            "players": 19
        },
        {
            "id": 236284,
            "title": "BLU vs RED",
            "map": "cp_metalworks_rc5",
            "date": 1396867124,
            "views": 221,
            "players": 12
        },
        {
            "id": 82681,
            "title": "Zen Auto Uploaded Log",
            "map": "koth_arctic_b3",
            "date": 1377600454,
            "views": 365,
            "players": 18
        }
    ]
}